<?xml version="1.0" encoding="UTF-8"?>
<definitions xmlns="http://www.omg.org/spec/BPMN/20100524/MODEL" xmlns:xsi="http://www.w3.org/2001/XMLSchema-instance" xmlns:xsd="http://www.w3.org/2001/XMLSchema" xmlns:activiti="http://activiti.org/bpmn" xmlns:bpmndi="http://www.omg.org/spec/BPMN/20100524/DI" xmlns:omgdc="http://www.omg.org/spec/DD/20100524/DC" xmlns:omgdi="http://www.omg.org/spec/DD/20100524/DI" xmlns:bpmn="http://www.omg.org/spec/BPMN/20100524/MODEL" xmlns:dc="http://www.omg.org/spec/DD/20100524/DC" xmlns:di="http://www.omg.org/spec/DD/20100524/DI" typeLanguage="http://www.w3.org/2001/XMLSchema" expressionLanguage="http://www.w3.org/1999/XPath" targetNamespace="http://bpmn.io/schema/bpmn" id="Definitions_0v7t65f">
  <process id="categorizeProcess" name="categorizeProcess" isExecutable="true">
    <startEvent id="StartEvent_1"></startEvent>
    <userTask id="usertask1" name="User Task" activiti:candidateGroups="activitiTeam"></userTask>
    <sequenceFlow id="flow1" sourceRef="StartEvent_1" targetRef="usertask1"></sequenceFlow>
    <endEvent id="endevent1" name="End"></endEvent>
    <sequenceFlow id="flow2" sourceRef="usertask1" targetRef="endevent1"></sequenceFlow>
  </process>
  <bpmndi:BPMNDiagram id="BPMNDiagram_categorizeProcess">
    <bpmndi:BPMNPlane bpmnElement="categorizeProcess" id="BPMNPlane_categorizeProcess">
      <bpmndi:BPMNShape bpmnElement="StartEvent_1" id="BPMNShape_StartEvent_1">
        <omgdc:Bounds height="36.0" width="36.0" x="270.0" y="190.0"></omgdc:Bounds>
      </bpmndi:BPMNShape>
      <bpmndi:BPMNShape bpmnElement="usertask1" id="BPMNShape_usertask1">
        <omgdc:Bounds height="55.0" width="105.0" x="350.0" y="180.0"></omgdc:Bounds>
      </bpmndi:BPMNShape>
      <bpmndi:BPMNShape bpmnElement="endevent1" id="BPMNShape_endevent1">
        <omgdc:Bounds height="35.0" width="35.0" x="500.0" y="190.0"></omgdc:Bounds>
      </bpmndi:BPMNShape>
      <bpmndi:BPMNEdge bpmnElement="flow1" id="BPMNEdge_flow1">
        <omgdi:waypoint x="306.0" y="208.0"></omgdi:waypoint>
        <omgdi:waypoint x="350.0" y="207.0"></omgdi:waypoint>
      </bpmndi:BPMNEdge>
      <bpmndi:BPMNEdge bpmnElement="flow2" id="BPMNEdge_flow2">
        <omgdi:waypoint x="455.0" y="207.0"></omgdi:waypoint>
        <omgdi:waypoint x="500.0" y="207.0"></omgdi:waypoint>
      </bpmndi:BPMNEdge>
    </bpmndi:BPMNPlane>
  </bpmndi:BPMNDiagram>
</definitions>
